{
  "name": "Template",
  "type": "ARM",
  "dependenceList": [],
  "srcDirs": [],
  "virtualFolder": {
    "name": "<virtual_root>",
    "files": [],
    "folders": [
      {
        "name": "USER",
        "files": [
          {
            "path": "main.c"
          },
          {
            "path": "stm32f4xx_it.c"
          },
          {
            "path": "system_stm32f4xx.c"
          }
        ],
        "folders": []
      },
      {
        "name": "CORE",
        "files": [
          {
            "path": "../CORE/startup_stm32f40_41xxx.s"
          }
        ],
        "folders": []
      },
      {
        "name": "FWLIB",
        "files": [
          {
            "path": "../FWLIB/src/misc.c"
          },
          {
            "path": "../FWLIB/src/stm32f4xx_adc.c"
          },
          {
            "path": "../FWLIB/src/stm32f4xx_can.c"
          },
          {
            "path": "../FWLIB/src/stm32f4xx_crc.c"
          },
          {
            "path": "../FWLIB/src/stm32f4xx_cryp.c"
          },
          {
            "path": "../FWLIB/src/stm32f4xx_cryp_aes.c"
          },
          {
            "path": "../FWLIB/src/stm32f4xx_cryp_des.c"
          },
          {
            "path": "../FWLIB/src/stm32f4xx_cryp_tdes.c"
          },
          {
            "path": "../FWLIB/src/stm32f4xx_dac.c"
          },
          {
            "path": "../FWLIB/src/stm32f4xx_dbgmcu.c"
          },
          {
            "path": "../FWLIB/src/stm32f4xx_dcmi.c"
          },
          {
            "path": "../FWLIB/src/stm32f4xx_dma2d.c"
          },
          {
            "path": "../FWLIB/src/stm32f4xx_dma.c"
          },
          {
            "path": "../FWLIB/src/stm32f4xx_exti.c"
          },
          {
            "path": "../FWLIB/src/stm32f4xx_flash.c"
          },
          {
            "path": "../FWLIB/src/stm32f4xx_flash_ramfunc.c"
          },
          {
            "path": "../FWLIB/src/stm32f4xx_fsmc.c"
          },
          {
            "path": "../FWLIB/src/stm32f4xx_gpio.c"
          },
          {
            "path": "../FWLIB/src/stm32f4xx_hash.c"
          },
          {
            "path": "../FWLIB/src/stm32f4xx_hash_md5.c"
          },
          {
            "path": "../FWLIB/src/stm32f4xx_hash_sha1.c"
          },
          {
            "path": "../FWLIB/src/stm32f4xx_i2c.c"
          },
          {
            "path": "../FWLIB/src/stm32f4xx_iwdg.c"
          },
          {
            "path": "../FWLIB/src/stm32f4xx_ltdc.c"
          },
          {
            "path": "../FWLIB/src/stm32f4xx_pwr.c"
          },
          {
            "path": "../FWLIB/src/stm32f4xx_rcc.c"
          },
          {
            "path": "../FWLIB/src/stm32f4xx_rng.c"
          },
          {
            "path": "../FWLIB/src/stm32f4xx_rtc.c"
          },
          {
            "path": "../FWLIB/src/stm32f4xx_sai.c"
          },
          {
            "path": "../FWLIB/src/stm32f4xx_sdio.c"
          },
          {
            "path": "../FWLIB/src/stm32f4xx_spi.c"
          },
          {
            "path": "../FWLIB/src/stm32f4xx_syscfg.c"
          },
          {
            "path": "../FWLIB/src/stm32f4xx_tim.c"
          },
          {
            "path": "../FWLIB/src/stm32f4xx_usart.c"
          },
          {
            "path": "../FWLIB/src/stm32f4xx_wwdg.c"
          }
        ],
        "folders": []
      },
      {
        "name": "SYSTEM",
        "files": [
          {
            "path": "../SYSTEM/delay/delay.c"
          },
          {
            "path": "../SYSTEM/sys/sys.c"
          }
        ],
        "folders": []
      },
      {
        "name": "README",
        "files": [
          {
            "path": "../readme.txt"
          }
        ],
        "folders": []
      },
      {
        "name": "HARDWORE",
        "files": [
          {
            "path": "../HARDWORE/pwm/pwm.c"
          },
          {
            "path": "../HARDWORE/timer/timer.c"
          },
          {
            "path": "../HARDWORE/LED/led.c"
          },
          {
            "path": "NRF24L01.c"
          },
          {
            "path": "OLED.c"
          },
          {
            "path": "gpio.c"
          },
          {
            "path": "../HARDWORE/Encoder/encoder.c"
          },
          {
            "path": "../HARDWORE/Encoder/encoder.h"
          },
          {
            "path": "../SYSTEM/usart/usart.c"
          },
          {
            "path": "../SYSTEM/usart/usart.h"
          },
          {
            "path": "../HARDWORE/sg90/sg90.c"
          },
          {
            "path": "../HARDWORE/sg90/sg90.h"
          },
          {
            "path": "../HARDWORE/pid/pid.h"
          },
          {
            "path": "../HARDWORE/pid/pid.c"
          },
          {
            "path": "../HARDWORE/oledfront.h"
          },
          {
            "path": "OLED_Font.h"
          },
          {
            "path": "BME.c"
          },
          {
            "path": "BME.h"
          },
          {
            "path": "MyI2C.c"
          },
          {
            "path": "MyI2C.h"
          },
          {
            "path": "Serial.c"
          },
          {
            "path": "Serial.h"
          }
        ],
        "folders": []
      }
    ]
  },
  "outDir": "build",
  "deviceName": null,
  "packDir": null,
  "miscInfo": {
    "uid": "cbebd0610a8419dfc25dd95893feb9d4"
  },
  "targets": {
    "Template": {
      "excludeList": [],
      "toolchain": "AC5",
      "compileConfig": {
        "cpuType": "Cortex-M4",
        "archExtensions": "",
        "floatingPointHardware": "single",
        "scatterFilePath": "",
        "useCustomScatterFile": false,
        "storageLayout": {
          "RAM": [
            {
              "tag": "RAM",
              "id": 1,
              "mem": {
                "startAddr": "0x0",
                "size": "0x0"
              },
              "isChecked": false,
              "noInit": false
            },
            {
              "tag": "RAM",
              "id": 2,
              "mem": {
                "startAddr": "0x0",
                "size": "0x0"
              },
              "isChecked": false,
              "noInit": false
            },
            {
              "tag": "RAM",
              "id": 3,
              "mem": {
                "startAddr": "0x0",
                "size": "0x0"
              },
              "isChecked": false,
              "noInit": false
            },
            {
              "tag": "IRAM",
              "id": 1,
              "mem": {
                "startAddr": "0x20000000",
                "size": "0x20000"
              },
              "isChecked": true,
              "noInit": false
            },
            {
              "tag": "IRAM",
              "id": 2,
              "mem": {
                "startAddr": "0x10000000",
                "size": "0x10000"
              },
              "isChecked": false,
              "noInit": false
            }
          ],
          "ROM": [
            {
              "tag": "ROM",
              "id": 1,
              "mem": {
                "startAddr": "0x0",
                "size": "0x0"
              },
              "isChecked": false,
              "isStartup": false
            },
            {
              "tag": "ROM",
              "id": 2,
              "mem": {
                "startAddr": "0x0",
                "size": "0x0"
              },
              "isChecked": false,
              "isStartup": false
            },
            {
              "tag": "ROM",
              "id": 3,
              "mem": {
                "startAddr": "0x0",
                "size": "0x0"
              },
              "isChecked": false,
              "isStartup": false
            },
            {
              "tag": "IROM",
              "id": 1,
              "mem": {
                "startAddr": "0x8000000",
                "size": "0x100000"
              },
              "isChecked": true,
              "isStartup": true
            },
            {
              "tag": "IROM",
              "id": 2,
              "mem": {
                "startAddr": "0x0",
                "size": "0x0"
              },
              "isChecked": false,
              "isStartup": false
            }
          ]
        },
        "options": "null"
      },
      "uploader": "JLink",
      "uploadConfig": {
        "bin": "",
        "baseAddr": "",
        "cpuInfo": {
          "vendor": "null",
          "cpuName": "null"
        },
        "proType": 1,
        "speed": 8000,
        "otherCmds": ""
      },
      "uploadConfigMap": {},
      "custom_dep": {
        "name": "default",
        "incList": [
          "../CORE",
          "../SYSTEM/delay",
          "../SYSTEM/sys",
          "../SYSTEM/usart",
          ".",
          "../FWLIB/inc",
          "../HARDWORE/pwm",
          "../HARDWORE/timer",
          "../HARDWORE/Gyro",
          "../HARDWORE/LED",
          "../HARDWORE/IIC",
          "../HARDWORE/MS5837",
          "../HARDWORE/move",
          "../HARDWORE/HC05",
          "../HARDWORE/exti",
          "../HARDWORE/Encoder",
          ".cmsis/include",
          "RTE/_Template"
        ],
        "libList": [],
        "defineList": [
          "STM32F40_41xxx",
          "USE_STDPERIPH_DRIVER"
        ]
      },
      "builderOptions": {
        "AC5": {
          "version": 4,
          "beforeBuildTasks": [],
          "afterBuildTasks": [],
          "global": {
            "use-microLIB": true,
            "output-debug-info": "enable"
          },
          "c/cpp-compiler": {
            "optimization": "level-0",
            "one-elf-section-per-function": true,
            "c99-mode": true,
            "C_FLAGS": "--diag_suppress=1 --diag_suppress=1295",
            "CXX_FLAGS": "--diag_suppress=1 --diag_suppress=1295",
            "warnings": "unspecified"
          },
          "asm-compiler": {},
          "linker": {
            "$outputTaskExcludes": [
              ".bin"
            ],
            "output-format": "elf",
            "xo-base": "",
            "ro-base": "0x08000000",
            "rw-base": "0x20000000"
          }
        }
      }
    }
  },
  "version": "3.6"
}